{
    "data": [
      {
        "id": "1",
        "name": "Indian Cuisine",
        "dishes": [
          {
            "id": "1",
            "name": "Pav Bhaji",
            "ingredients": [
              { "id": "1", "name": "Pav" },
              { "id": "2", "name": "Cauliflower" },
              { "id": "3", "name": "Green Pees" },
              { "id": "4", "name": "Tomato" },
              { "id": "5", "name": "Potato" },
              { "id": "6", "name": "Onion" },
              { "id": "7", "name": "Ginger" },
              { "id": "8", "name": "Garlic" },
              { "id": "9", "name": "Butter" },
              { "id": "10", "name": "Masala" }
            ]
          },
          {
            "id": "2",
            "name": "Chhole Bature",
            "ingredients": [
              { "id": "1", "name": "Maida" },
              { "id": "2", "name": "Chhole" },
              { "id": "3", "name": "Chana" },
              { "id": "4", "name": "Tomato" },
              { "id": "5", "name": "Green Chilli" },
              { "id": "6", "name": "Onion" },
              { "id": "7", "name": "Ginger" },
              { "id": "8", "name": "Garlic" },
              { "id": "9", "name": "Butter" },
              { "id": "10", "name": "Masala" }
            ]
          },
          {
            "id": "3",
            "name": "Chicken Curry",
            "ingredients": [
              { "id": "1", "name": "Chicken" },
              { "id": "2", "name": "Oil" },
              { "id": "3", "name": "Chicken Masala" },
              { "id": "4", "name": "Tomato" },
              { "id": "5", "name": "Green Chilli" },
              { "id": "6", "name": "Onion" },
              { "id": "7", "name": "Ginger" },
              { "id": "8", "name": "Garlic" },
              { "id": "9", "name": "Butter" },
              { "id": "10", "name": "Masala" }
            ]
          }
        ]
      },
      {
        "id": "2",
        "name": "Chinese Cuisine",
        "dishes": [
          {
            "id": "1",
            "name": "Schejwan Noodles",
            "ingredients": [
              { "id": "1", "name": "Noodles" },
              { "id": "2", "name": "Cauliflower" },
              { "id": "3", "name": "Cabage" },
              { "id": "4", "name": "Tomato" },
              { "id": "5", "name": "Schejwan Masala" },
              { "id": "6", "name": "Onion" },
              { "id": "7", "name": "Ginger" },
              { "id": "8", "name": "Garlic" },
              { "id": "9", "name": "Butter" },
              { "id": "10", "name": "Masala" }
            ]
          },
          {
            "id": "2",
            "name": "Veg Manchurian",
            "ingredients": [
              { "id": "1", "name": "Maida" },
              { "id": "2", "name": "Manchurian" },
              { "id": "3", "name": "Cabage" },
              { "id": "4", "name": "Cauliflower" },
              { "id": "5", "name": "Green Chilli" },
              { "id": "6", "name": "Onion" },
              { "id": "7", "name": "Ginger" },
              { "id": "8", "name": "Garlic" },
              { "id": "9", "name": "Butter" },
              { "id": "10", "name": "Masala" }
            ]
          },
          {
            "id": "3",
            "name": "Fried Rice",
            "ingredients": [
              { "id": "1", "name": "Boiled Rice" },
              { "id": "2", "name": "Oil" },
              { "id": "3", "name": "Schejwan Masala" },
              { "id": "4", "name": "Tomato" },
              { "id": "5", "name": "Green Chilli" },
              { "id": "6", "name": "Onion" },
              { "id": "7", "name": "Ginger" },
              { "id": "8", "name": "Garlic" },
              { "id": "9", "name": "Butter" },
              { "id": "10", "name": "Masala" }
            ]
          }
        ]
      },
      {
        "id": "3",
        "name": "Italian Cuisine",
        "dishes": [
          {
            "id": "1",
            "name": "Margherita Pizza",
            "ingredients": [
              { "id": "1", "name": "Pizza Dough" },
              { "id": "2", "name": "San Marzano Tomatoes" },
              { "id": "3", "name": "Mozzarella Balls" },
              { "id": "4", "name": "Fresh Basils" },
              { "id": "5", "name": "Olive Oil" },
              { "id": "6", "name": "Salt" },
              { "id": "7", "name": "Masala" }
            ]
          },
          {
            "id": "2",
            "name": "Pasta",
            "ingredients": [
              { "id": "1", "name": "Penne" },
              { "id": "2", "name": "Macaroni" },
              { "id": "3", "name": "Fusilli" },
              { "id": "4", "name": "Rigatoni" },
              { "id": "5", "name": "Elbow" },
              { "id": "6", "name": "Onion" },
              { "id": "7", "name": "Carrot" },
              { "id": "8", "name": "Peas" },
              { "id": "9", "name": "Salt" },
              { "id": "10", "name": "Oil" }
            ]
          }
        ]
      }
    ]
  }
   